migrations/README
migrations/__init__.py
migrations/alembic.ini
migrations/env.py
realnet_server/__init__.py
realnet_server/__main__.py
realnet_server/accounts.py
realnet_server/apps.py
realnet_server/auth.py
realnet_server/authenticators.py
realnet_server/config.py
realnet_server/core.py
realnet_server/groups.py
realnet_server/import_file.py
realnet_server/items.py
realnet_server/mobile.py
realnet_server/models.py
realnet_server/notifications.py
realnet_server/oauth.py
realnet_server/people.py
realnet_server/realnet_server.py
realnet_server/tenants.py
realnet_server/types.py
realnet_server/modules/__init__.py
realnet_server/modules/default.py
realnet_server/modules/filesystem.py
realnet_server/modules/module.py
realnet_server/modules/person.py
realnet_server/resources/__init__.py
realnet_server/resources/items.csv
realnet_server/resources/types.json
realnet_server/templates/__init__.py
realnet_server/templates/authorize.html
realnet_server/templates/create_client.html
realnet_server/templates/home.html
realnet_server/templates/login.html
realnet_server/templates/register.html
realnet_server/templates/settings.html
realnet_wsgi_loader/__init__.py
realnet_wsgi_loader/wsgi.py
realnet_server-0.0.9.dist-info/LICENSE
realnet_server-0.0.9.dist-info/METADATA
realnet_server-0.0.9.dist-info/WHEEL
realnet_server-0.0.9.dist-info/entry_points.txt
realnet_server-0.0.9.dist-info/top_level.txt
realnet_server-0.0.9.dist-info/RECORD
