Metadata-Version: 2.1
Name: realnet-server
Version: 0.0.9
Summary: Realnet server
Home-page: https://github.com/virtual-space/realnet-server
Author: Marko Laban
Author-email: marko.laban@l33tsystems.com
License: BSD
Platform: UNKNOWN
Classifier: License :: OSI Approved :: BSD License
Classifier: Programming Language :: Python :: 3
Classifier: Programming Language :: Python :: 3.7
Requires-Dist: pynecone (==0.0.70)
Requires-Dist: requests-toolbelt
Requires-Dist: python-dotenv
Requires-Dist: requests
Requires-Dist: flask
Requires-Dist: bootstrap-flask
Requires-Dist: flask-migrate
Requires-Dist: flask-sqlalchemy
Requires-Dist: flask-cors
Requires-Dist: flask-script
Requires-Dist: sqlalchemy-serializer
Requires-Dist: shapely
Requires-Dist: GeoAlchemy2
Requires-Dist: psycopg2-binary
Requires-Dist: random-password-generator
Requires-Dist: authlib
Requires-Dist: pyyaml
Requires-Dist: boto3
